LICENSE.txt
MANIFEST.in
README.md
pyproject.toml
src/danoan/quick_notes/__init__.py
src/danoan/quick_notes/api/__init__.py
src/danoan/quick_notes/api/model.py
src/danoan/quick_notes/api/to_markdown.py
src/danoan/quick_notes/api/to_toml.py
src/danoan/quick_notes/api/templates/quick-note-table.tpl.md
src/danoan/quick_notes/cli/cli.py
src/danoan/quick_notes/cli/model.py
src/quick_notes.egg-info/PKG-INFO
src/quick_notes.egg-info/SOURCES.txt
src/quick_notes.egg-info/dependency_links.txt
src/quick_notes.egg-info/entry_points.txt
src/quick_notes.egg-info/requires.txt
src/quick_notes.egg-info/top_level.txt
test/test_cli.py
test/test_parsers.py