Metadata-Version: 2.4
Name: quick-notes
Version: 1.0.1
Summary: Markdown dialect with support to metadata and toml serialization
Author-email: Daniel Martins Antunes <danoan2008@gmail.com>
License: MIT License
Project-URL: Documentation, https://github.com/danoan/quick-notes#readme
Project-URL: Issues, https://github.com/danoan/quick-notes/issues
Project-URL: Source, https://github.com/danoan/quick-notes
Classifier: Development Status :: 4 - Beta
Classifier: Programming Language :: Python
Classifier: Programming Language :: Python :: 3.8
Classifier: Programming Language :: Python :: Implementation :: CPython
Classifier: Programming Language :: Python :: Implementation :: PyPy
Requires-Python: >=3.8
License-File: LICENSE.txt
Requires-Dist: dataclasses
Requires-Dist: jinja2
Requires-Dist: typing_extensions
Requires-Dist: importlib_resources
Requires-Dist: lark
Requires-Dist: toml_dataclass
Dynamic: license-file
